Data_Save/__init__.py
Data_Save/data.py
Data_Save-1.0.0.dist-info/METADATA
Data_Save-1.0.0.dist-info/WHEEL
Data_Save-1.0.0.dist-info/top_level.txt
Data_Save-1.0.0.dist-info/RECORD
