Metadata-Version: 2.1
Name: Data-Save
Version: 1.0.0
Summary: Save Data
Author: px228
Author-email: leka55mapket@gmail.com
Classifier: Programming Language :: Python :: 3
Classifier: License :: OSI Approved :: MIT License
Classifier: Operating System :: OS Independent
Requires-Python: >=3.6
